[{"id":6,"title":"MDK","category":"Action","url":"/en/game/mdk","image":"//images-3.gog-statics.com/c02a5a3b627f4682a672f14b716334a9b37acc554308852396c3b6fc89ee405d","price":{"ES":"10.06"},"sale":{"ES":"8.04"},"discount-rate":0},{"id":1162267648,"title":"Project Highrise: Architect's Edition","category":"Simulation","url":"/en/game/project_highrise_architects_edition","image":"//images-3.gog-statics.com/3eab881da7afc3cd86b1309793a1af8c1694d2ed38bf898144b003477625f9d3","price":{"CX":"29.99","ES":"30.21"},"sale":{"CX":"22.49","ES":"22.65"},"discount-rate":0.71},{"id":1176929400,"title":"Medal of Honor™: Pacific Assault","category":"Shooter","url":"/en/game/medal_of_honor_pacific_assault","image":"//images-1.gog-statics.com/8e13aeef741dfe3f75f57fac388221c9b5b946ca37adcf48e523626e9ecfb43b","price":{"ES":"9.99"},"sale":{"ES":"2.49"},"discount-rate":0},{"id":1207658645,"title":"MDK 2","category":"Action","url":"/en/game/mdk_2","image":"//images-3.gog-statics.com/727c27ece9944d7873210bee007a94f76783fb68afbb1d1fc33fe5cde826f5cf","price":{"ES":"10.06"},"sale":{"ES":"8.04"},"discount-rate":0},{"id":1207658747,"title":"Prince of Persia®: The Sands of Time","category":"Action","url":"/en/game/prince_of_persia_the_sands_of_time","image":"//images-3.gog-statics.com/b39f745aea99e997ec9eb2052761bdb3e93985e8eb07c23b54c86c448350da9f","price":{"CX":"9.99","ES":"10.06"},"sale":{"CX":"1.69","ES":"1.71"},"discount-rate":1.17},{"id":1207658758,"title":"MegaRace 1+2","category":"Racing","url":"/en/game/megarace_1_2","image":"//images-1.gog-statics.com/4a0dddd37410e093bb134564ddd19308cea527c0ce9ca8a3cca91195c6b8fa12","price":{"ES":"5.99"},"sale":{"ES":"0.59"},"discount-rate":0},{"id":1207658764,"title":"MegaRace 3","category":"Racing","url":"/en/game/megarace_3","image":"//images-2.gog-statics.com/1ceb89d93f00231ee6e840a1c988cf4f1b99033390560b0f04df1e1ce382dade","price":{"DZ":"2.99","ES":"3.02"},"sale":{"DZ":"0.59","ES":"0.60"},"discount-rate":1.67},{"id":1207658773,"title":"Personal Nightmare","category":"Adventure","url":"/en/game/personal_nightmare","image":"//images-3.gog-statics.com/4ae8f11e287489a31297928db6cb48d9dc7958771142868de5285a374c04befc","price":{"ES":"5.99","BE":"5.99","CA":"5.99"},"sale":{"ES":"1.49","BE":"1.49","CA":"1.49"},"discount-rate":0},{"id":1207658937,"title":"Ultima™ Underworld 1+2","category":"Role-playing","url":"/en/game/ultima_underworld_1_2","image":"//images-3.gog-statics.com/d72b0c7295fe255b2a292dfb52654213d7d119e0e2a17020144583621330eb1d","price":{"ES":"5.99"},"sale":{"ES":"1.49"},"discount-rate":0},{"id":1207658984,"title":"Ultima™ 7 The Complete Edition","category":"Role-playing","url":"/en/game/ultima_7_complete","image":"//images-1.gog-statics.com/7a843f83496e360981b771c636119ad127943b1666517163f20227f389dee060","price":{"ES":"5.99"},"sale":{"ES":"1.37"},"discount-rate":0},{"id":1207659015,"title":"Ultima™ 8 Gold Edition","category":"Role-playing","url":"/en/game/ultima_8_gold_edition","image":"//images-2.gog-statics.com/4dab7e128c02e2024887b33afed7583f6212b7dacb93640b296491d6d2b706d6","price":{"ES":"5.99"},"sale":{"ES":"1.49"},"discount-rate":0},{"id":1207659082,"title":"Prince of Persia: Warrior Within","category":"Action","url":"/en/game/prince_of_persia_warrior_within","image":"//images-3.gog-statics.com/80b9c3f18cb3c38c0afe796a43e3eadf5482b2388f09ea5a5102adc70a90dd7e","price":{"CX":"9.99","ES":"10.06"},"sale":{"CX":"1.99","ES":"2.01"},"discount-rate":1},{"id":1207659091,"title":"Prince of Persia: The Two Thrones","category":"Action","url":"/en/game/prince_of_persia_the_two_thrones","image":"//images-4.gog-statics.com/dbff543e65d4b28e73efca18e0c395a1d3bffadee59513fff00ea3d83735f6c8","price":{"CX":"9.99","ES":"10.06"},"sale":{"CX":"1.99","ES":"2.01"},"discount-rate":1},{"id":1207659093,"title":"Ultima™ 9: Ascension","category":"Role-playing","url":"/en/game/ultima_9_ascension","image":"//images-2.gog-statics.com/c1b9ab8a4bf96544aaa2c19605a7b8f5a3a031fb96c812399554a93e6584c160","price":{"ES":"5.99"},"sale":{"ES":"1.49"},"discount-rate":0},{"id":1207659109,"title":"Prince of Persia","category":"Action","url":"/en/game/prince_of_persia","image":"//images-1.gog-statics.com/465413237cb962d9b0ded6b3eaaaa96ea78d029c39b68f00e10f3727fad7f7e3","price":{"CX":"9.99","ES":"10.06"},"sale":{"CX":"1.99","ES":"2.01"},"discount-rate":1},{"id":1207659126,"title":"Medal of Honor: Allied Assault War Chest","category":"Shooter","url":"/en/game/medal_of_honor_allied_assault_war_chest","image":"//images-3.gog-statics.com/5c91eb2e789f75422df7dbd85964dddcd38d90102db901049c48882d1fce26a2","price":{"ES":"9.99"},"sale":{"ES":"2.49"},"discount-rate":0},{"id":1207659144,"title":"Primordia","category":"Adventure","url":"/en/game/primordia","image":"//images-4.gog-statics.com/fae2a98995099d6460704772c64d3aa2f42e13ab75bdf90ee7cca88abe1633f2","price":{"CX":"9.99","ES":"10.06"},"sale":{"CX":"2.99","ES":"3.01"},"discount-rate":0.66},{"id":1207659613,"title":"Privateer 2: The Darkening","category":"Shooter","url":"/en/game/privateer_2_the_darkening","image":"//images-2.gog-statics.com/7d71a896ff4318613f2d9e33a82b7125a6bd3ef24b87c7f082c59c1a96c8f579","price":{"ES":"5.99","CX":"5.99"},"sale":{"ES":"1.49","CX":"1.49"},"discount-rate":0},{"id":1207659803,"title":"Memoria","category":"Adventure","url":"/en/game/memoria","image":"//images-1.gog-statics.com/8cd8ee0340dc6ef06126ad97dadeb91206fde33fadc1371f26fe917c1e76d3e3","price":{"DZ":"19.99","ES":"20.15"},"sale":{"DZ":"1.99","ES":"2.01"},"discount-rate":1},{"id":1246381210,"title":"Pikuniku","category":"Adventure","url":"/en/game/pikuniku","image":"//images-1.gog-statics.com/8a00026186a92125265f56006bab13eddf3ce4eab0dee74f4a81c429cda1fcbf","price":{"CA":"10.76","ES":"10.88","BE":"10.88"},"sale":{"CA":"2.69","ES":"2.72","BE":"2.72"},"discount-rate":1.1},{"id":1273860392,"title":"Prince of Qin","category":"Action","url":"/en/game/prince_of_qin","image":"//images-1.gog-statics.com/2cdfddd3dec7917c09b757932786d2c4409d718ffd4168f02498104916f7e718","price":{"ES":"8.26","CX":"9.99"},"sale":{"ES":"1.23","CX":"1.49"},"discount-rate":0},{"id":1322614388,"title":"Universe Sandbox","category":"Simulation","url":"/en/game/universe_sandbox","image":"//images-3.gog-statics.com/f3be7ecbc3908dfecf7e84d855f2d240ac823daecba4e7ea598a0e68b422256b","price":{"ES":"25.18"},"sale":{"ES":"16.87"},"discount-rate":0},{"id":1373563527,"title":"Pikuniku Collector's Edition","category":"Adventure","url":"/en/game/pikuniku_collectors_edition","image":"//images-4.gog-statics.com/b5f43700dd712a7dd1f7dc7d1fff5c8ac4b8db3135dd2170fd0324f5a9c6444e","price":{"CA":"4.97","ES":"5.02","BE":"5.02"},"sale":{"CA":"1.24","ES":"1.25","BE":"1.25"},"discount-rate":0.8},{"id":1378946365,"title":"Unforeseen Incidents","category":"Adventure","url":"/en/game/unforeseen_incidents","image":"//images-3.gog-statics.com/659f6dce4d28d935c90c034dae497e771e3052a117a5fae7d8cfb9dba594fdae","price":{"ES":"20.15"},"sale":{"ES":"12.09"},"discount-rate":0},{"id":1454498998,"title":"Perimeter: Emperor's Testament","category":"Strategy","url":"/en/game/perimeter_emperors_testament","image":"//images-3.gog-statics.com/0806bd4f43e39d7d247163fd964c53b741223baa8f4df2cec8ebcbf33ecd78c7","price":{"CA":"3.34","ES":"4.03","BE":"4.03"},"sale":{"CA":"0.66","ES":"0.80","BE":"0.80"},"discount-rate":17.5},{"id":1553649691,"title":"Lollypop","category":"Action","url":"/en/game/lollypop","image":"//images-1.gog-statics.com/0549ebb6836d03f398a80e4589b3eec37d1d9e0c3b1430b7dfef2c2e9b07a2cf","price":{"ES":"5.74","TL":"6.99"},"sale":{"ES":"3.84","TL":"4.68"},"discount-rate":0},{"id":1571977582,"title":"Meat Puppet","category":"Action","url":"/en/game/meat_puppet","image":"//images-4.gog-statics.com/4f9c2f95c1753122a65d4aceb2066cb9c1312b048a3fcc1cd2d786408acc0ca1","price":{"ES":"8.05"},"sale":{"ES":"6.03"},"discount-rate":0},{"id":1637485057,"title":"Unavowed","category":"Adventure","url":"/en/game/unavowed","image":"//images-1.gog-statics.com/acc4ba0436e84b42ff5efbde5498801d97fe3adb863e0ab7111f815428308dbf","price":{"ES":"15.10"},"sale":{"ES":"6.79"},"discount-rate":0},{"id":1740243150,"title":"Lords and Villeins","category":"Simulation","url":"/en/game/lords_and_villeins","image":"//images-4.gog-statics.com/e608c0c8e13aaa34fe318115cc733cdef251c61757ec04c502eac91bfb5e1e4e","price":{"TL":"24.99","ES":"25.18"},"sale":{"TL":"19.99","ES":"20.14"},"discount-rate":0.74},{"id":1811787702,"title":"Prodigy Tactics","category":"Strategy","url":"/en/game/prodigy_tactics","image":"//images-1.gog-statics.com/8b71b85d8ca985a8308d1dd43d2ff69a359cdf09d8456a9fd992a771baa1c5ad","price":{"CX":"19.99","ES":"20.15"},"sale":{"CX":"1.99","ES":"2.01"},"discount-rate":1},{"id":1896497767,"title":"Loop Hero","category":"Role-playing","url":"/en/game/loop_hero","image":"//images-1.gog-statics.com/fdaa21ea2bb79331e5c924e515a90879cab09d22d932919e36e17a891d941f82","price":{"TL":"14.99","ES":"15.10"},"sale":{"TL":"4.94","ES":"4.98"},"discount-rate":0.8},{"id":1983831346,"title":"Lost At Sea","category":"Adventure","url":"/en/game/lost_at_sea","image":"//images-2.gog-statics.com/008aa3218b77104d078572bbf77d82f904c14c817db762ca66175b9e8ca94969","price":{"TL":"14.99","ES":"15.10"},"sale":{"TL":"3.74","ES":"3.77"},"discount-rate":0.8},{"id":2018730457,"title":"Project Highrise","category":"Simulation","url":"/en/game/project_highrise","image":"//images-1.gog-statics.com/ba84079ec7d19f4ad059786042f465b905c6998a1e306fbd32f899bf5156af96","price":{"CX":"19.99","ES":"20.15"},"sale":{"CX":"4.99","ES":"5.03"},"discount-rate":0.8},{"id":2056114425,"title":"7 Billion Humans","category":"Simulation","url":"/en/game/7_billion_humans","image":"//images-2.gog-statics.com/bfab119ebeb03ba17d7352f88ea039cc6bbb2a421b6456ef414964e180b1ef47","price":{"AR":"4.74","BO":"4.74","BR":"4.74","CL":"4.74","CO":"4.74","CR":"4.74","DO":"4.74","EC":"4.74","SV":"4.74","RU":"4.88","CN":"6.71","AU":"11.67","DK":"14.09","ES":"14.10","AD":"14.10","AT":"14.10","BE":"14.10","BG":"14.10","HR":"14.10","CY":"14.10","CZ":"14.10","AF":"14.99","AX":"14.99","AL":"14.99","DZ":"14.99","AS":"14.99","AO":"14.99","AI":"14.99","AQ":"14.99","AG":"14.99","AM":"14.99","AW":"14.99","AZ":"14.99","BS":"14.99","BH":"14.99","BD":"14.99","BB":"14.99","BY":"14.99","BZ":"14.99","BJ":"14.99","BM":"14.99","BT":"14.99","BQ":"14.99","BA":"14.99","BW":"14.99","BV":"14.99","IO":"14.99","VG":"14.99","BN":"14.99","BF":"14.99","BI":"14.99","KH":"14.99","CM":"14.99","CA":"14.99","CV":"14.99","KY":"14.99","CF":"14.99","TD":"14.99","CX":"14.99","CC":"14.99","KM":"14.99","CK":"14.99","CU":"14.99","CW":"14.99","CD":"14.99","DJ":"14.99","DM":"14.99","TL":"14.99","EG":"14.99","ER":"14.99","FO":"14.99","PF":"14.99","GA":"14.99","GI":"14.99","KI":"14.99"},"sale":{"AR":"2.37","BO":"2.37","BR":"2.37","CL":"2.37","CO":"2.37","CR":"2.37","DO":"2.37","EC":"2.37","SV":"2.37","RU":"2.44","CN":"3.35","AU":"5.83","DK":"7.04","ES":"7.05","AD":"7.05","AT":"7.05","BE":"7.05","BG":"7.05","HR":"7.05","CY":"7.05","CZ":"7.05","AF":"7.49","AX":"7.49","AL":"7.49","DZ":"7.49","AS":"7.49","AO":"7.49","AI":"7.49","AQ":"7.49","AG":"7.49","AM":"7.49","AW":"7.49","AZ":"7.49","BS":"7.49","BH":"7.49","BD":"7.49","BB":"7.49","BY":"7.49","BZ":"7.49","BJ":"7.49","BM":"7.49","BT":"7.49","BQ":"7.49","BA":"7.49","BW":"7.49","BV":"7.49","IO":"7.49","VG":"7.49","BN":"7.49","BF":"7.49","BI":"7.49","KH":"7.49","CM":"7.49","CA":"7.49","CV":"7.49","KY":"7.49","CF":"7.49","TD":"7.49","CX":"7.49","CC":"7.49","KM":"7.49","CK":"7.49","CU":"7.49","CW":"7.49","CD":"7.49","DJ":"7.49","DM":"7.49","TL":"7.49","EG":"7.49","ER":"7.49","FO":"7.49","PF":"7.49","GA":"7.49","GI":"7.49","KI":"7.49"},"discount-rate":66.38},{"id":2065676798,"title":"Lost Eden","category":"Adventure","url":"/en/game/lost_eden","image":"//images-1.gog-statics.com/f9a1ec908c92bdc5860b9afe501d7893175ffd1191dc7f46db33ab0c32c82bc1","price":{"ES":"9.99","TL":"9.99"},"sale":{"ES":"7.99","TL":"7.99"},"discount-rate":0},{"id":2115164708,"title":"88 Heroes","category":"Action","url":"/en/game/88_heroes","image":"//images-2.gog-statics.com/31f103a918be21284e807a83212759f2c8da5c1cdf1add29fc561b8c8cdad624","price":{"AR":"5.31","BO":"5.31","BR":"5.31","CL":"5.31","CO":"5.31","CR":"5.31","DO":"5.31","EC":"5.31","SV":"5.31","RU":"5.69","AM":"5.69","AZ":"5.69","BY":"5.69","AU":"11.02","CA":"12.62","DK":"14.02","AF":"14.99","AX":"14.99","AL":"14.99","DZ":"14.99","AS":"14.99","AO":"14.99","AI":"14.99","AQ":"14.99","AG":"14.99","AW":"14.99","BS":"14.99","BH":"14.99","BD":"14.99","BB":"14.99","BZ":"14.99","BJ":"14.99","BM":"14.99","BT":"14.99","BQ":"14.99","BA":"14.99","BW":"14.99","BV":"14.99","IO":"14.99","VG":"14.99","BN":"14.99","BG":"14.99","BF":"14.99","BI":"14.99","KH":"14.99","CM":"14.99","CV":"14.99","KY":"14.99","CF":"14.99","TD":"14.99","CN":"14.99","CX":"14.99","CC":"14.99","KM":"14.99","CK":"14.99","HR":"14.99","CU":"14.99","CW":"14.99","CD":"14.99","DJ":"14.99","DM":"14.99","TL":"14.99","EG":"14.99","ER":"14.99","FO":"14.99","PF":"14.99","GA":"14.99","GI":"14.99","KI":"14.99","ES":"15.10","AD":"15.10","AT":"15.10","BE":"15.10","CY":"15.10","CZ":"15.10"},"sale":{"AR":"0.79","BO":"0.79","BR":"0.79","CL":"0.79","CO":"0.79","CR":"0.79","DO":"0.79","EC":"0.79","SV":"0.79","RU":"0.85","AM":"0.85","AZ":"0.85","BY":"0.85","AU":"1.65","CA":"1.89","DK":"2.10","AF":"2.24","AX":"2.24","AL":"2.24","DZ":"2.24","AS":"2.24","AO":"2.24","AI":"2.24","AQ":"2.24","AG":"2.24","AW":"2.24","BS":"2.24","BH":"2.24","BD":"2.24","BB":"2.24","BZ":"2.24","BJ":"2.24","BM":"2.24","BT":"2.24","BQ":"2.24","BA":"2.24","BW":"2.24","BV":"2.24","IO":"2.24","VG":"2.24","BN":"2.24","BG":"2.24","BF":"2.24","BI":"2.24","KH":"2.24","CM":"2.24","CV":"2.24","KY":"2.24","CF":"2.24","TD":"2.24","CN":"2.24","CX":"2.24","CC":"2.24","KM":"2.24","CK":"2.24","HR":"2.24","CU":"2.24","CW":"2.24","CD":"2.24","DJ":"2.24","DM":"2.24","TL":"2.24","EG":"2.24","ER":"2.24","FO":"2.24","PF":"2.24","GA":"2.24","GI":"2.24","KI":"2.24","ES":"2.26","AD":"2.26","AT":"2.26","BE":"2.26","CY":"2.26","CZ":"2.26"},"discount-rate":65.04}]